tejapi/__init__.py
tejapi/api_config.py
tejapi/connection.py
tejapi/fastget.py
tejapi/get.py
tejapi/message.py
tejapi/search_table.py
tejapi/util.py
tejapi/version.py
tejapi/errors/__init__.py
tejapi/errors/tej_error.py
tejapi/model/__init__.py
tejapi/model/data.py
tejapi/model/data_list.py
tejapi/model/data_mixin.py
tejapi/model/database.py
tejapi/model/datatable.py
tejapi/model/merged_data_list.py
tejapi/model/model_base.py
tejapi/model/model_list.py
tejapi/model/paginated_list.py
tejapi/operations/__init__.py
tejapi/operations/data_list.py
tejapi/operations/get.py
tejapi/operations/list.py
tejapi/operations/operation.py
tejapi/utils/__init__.py
tejapi/utils/api_key_util.py
tejapi-0.1.31.dist-info/METADATA
tejapi-0.1.31.dist-info/WHEEL
tejapi-0.1.31.dist-info/top_level.txt
tejapi-0.1.31.dist-info/RECORD
