Metadata-Version: 2.1
Name: tejapi
Version: 0.1.31
Summary: Package for access tej database from REST API
Home-page: https://api.tej.com.tw
Author: tej
Author-email: tej@tej.com.tw
Maintainer: tej api Development Team
Maintainer-email: tej@tej.com
License: MIT
Keywords: tej,API,data,financial,economic,stock,REST,database
Requires-Dist: pandas (>=0.18.1)
Requires-Dist: numpy (>=1.8)
Requires-Dist: requests (>=2.7.0)
Requires-Dist: inflection (>=0.3.1)
Requires-Dist: python-dateutil
Requires-Dist: six
Requires-Dist: more-itertools
Requires-Dist: fastparquet
